plurality/__init__.py
plurality-0.1.0.dist-info/METADATA
plurality-0.1.0.dist-info/WHEEL
plurality-0.1.0.dist-info/top_level.txt
plurality-0.1.0.dist-info/RECORD
