Metadata-Version: 2.4
Name: plurality
Version: 0.1.0
Summary: A minimal package to claim the plurality name on PyPI
Author-email: Plurality AI <contact@plurality.ai>
Project-URL: Homepage, https://github.com/pluralityai/plurality
Project-URL: Repository, https://github.com/pluralityai/plurality
Classifier: Development Status :: 3 - Alpha
Classifier: Intended Audience :: Developers
Classifier: License :: OSI Approved :: MIT License
Classifier: Programming Language :: Python :: 3
Classifier: Programming Language :: Python :: 3.8
Classifier: Programming Language :: Python :: 3.9
Classifier: Programming Language :: Python :: 3.10
Classifier: Programming Language :: Python :: 3.11
Classifier: Programming Language :: Python :: 3.12
Requires-Python: >=3.8
Requires-Dist: build>=1.2.2.post1
Requires-Dist: twine>=6.1.0
